simpleaudiocontroller/__init__.py
simpleaudiocontroller/__main__.py
simpleaudiocontroller/controller.py
simpleaudiocontroller/utils.py
simpleaudiocontroller-2.1.0.dist-info/LICENSE
simpleaudiocontroller-2.1.0.dist-info/METADATA
simpleaudiocontroller-2.1.0.dist-info/WHEEL
simpleaudiocontroller-2.1.0.dist-info/entry_points.txt
simpleaudiocontroller-2.1.0.dist-info/top_level.txt
simpleaudiocontroller-2.1.0.dist-info/RECORD
