Metadata-Version: 2.1
Name: simpleaudiocontroller
Version: 2.1.0
Summary: Simple interface for controlling audio devices
Home-page: https://github.com/andersonssh/simpleaudiocontroller
Author: Anderson Araújo
Author-email: andersondev.ssh@gmail.com
Classifier: Programming Language :: Python :: 3
Classifier: License :: OSI Approved :: MIT License
Classifier: Operating System :: Unix
Requires-Python: >=3.7
License-File: LICENSE
Requires-Dist: setuptools >=61.0
Provides-Extra: dev
Requires-Dist: pytest >=6.2.5 ; extra == 'dev'
Requires-Dist: black ; extra == 'dev'
Requires-Dist: isort ; extra == 'dev'
